minumtium_sqlite/__init__.py
minumtium_sqlite/migrations/__init__.py
minumtium_sqlite/migrations/versions/__init__.py
minumtium_sqlite/migrations/versions/version_0.py
minumtium_sqlite/migrations/versions/version_1.py
minumtium_sqlite-1.0.2.dist-info/LICENSE
minumtium_sqlite-1.0.2.dist-info/METADATA
minumtium_sqlite-1.0.2.dist-info/WHEEL
minumtium_sqlite-1.0.2.dist-info/top_level.txt
minumtium_sqlite-1.0.2.dist-info/RECORD
