Metadata-Version: 2.1
Name: minumtium-sqlite
Version: 1.0.2
Summary: A SQLite adapter for the minumtium library.
Home-page: https://github.com/danodic-dev/minumtium-sql-alchemy
Author: Danilo Guimaraes (danodic)
Author-email: danilo@danodic.dev
License: UNKNOWN
Project-URL: Bug Tracker, https://github.com/danodic-dev/minumtium-sql-alchemy/issues
Platform: UNKNOWN
Classifier: Development Status :: 3 - Alpha
Classifier: Programming Language :: Python :: 3
Classifier: License :: OSI Approved :: Apache Software License
Classifier: Operating System :: OS Independent
Requires-Python: >=3.6
License-File: LICENSE
Requires-Dist: sqlalchemy
Requires-Dist: minumtium
Requires-Dist: pydantic
